odoo/addons/contract_brand/README.rst
odoo/addons/contract_brand/__init__.py
odoo/addons/contract_brand/__manifest__.py
odoo/addons/contract_brand/i18n/contract_brand.pot
odoo/addons/contract_brand/i18n/es.po
odoo/addons/contract_brand/i18n/it.po
odoo/addons/contract_brand/models/__init__.py
odoo/addons/contract_brand/models/contract.py
odoo/addons/contract_brand/models/contract_line.py
odoo/addons/contract_brand/readme/CONTRIBUTORS.md
odoo/addons/contract_brand/readme/DESCRIPTION.md
odoo/addons/contract_brand/static/description/icon.png
odoo/addons/contract_brand/static/description/index.html
odoo/addons/contract_brand/tests/__init__.py
odoo/addons/contract_brand/tests/test_contract.py
odoo/addons/contract_brand/views/contract.xml
odoo_addon_contract_brand-18.0.1.0.0.7.dist-info/METADATA
odoo_addon_contract_brand-18.0.1.0.0.7.dist-info/WHEEL
odoo_addon_contract_brand-18.0.1.0.0.7.dist-info/top_level.txt
odoo_addon_contract_brand-18.0.1.0.0.7.dist-info/RECORD
